{
    "items": [
        {
            "pagePath": "/article/go/go-template/",
            "pv": "3"
        },
        {
            "pagePath": "/article/hugo/search/",
            "pv": "3"
        },
        {
            "pagePath": "/article/salt/blog-card/",
            "pv": "3"
        },
        {
            "pagePath": "/",
            "pv": "2"
        },
        {
            "pagePath": "/article/go/variable/",
            "pv": "1"
        },
        {
            "pagePath": "/article/salt/about/",
            "pv": "1"
        },
        {
            "pagePath": "/article/sample/markdown/",
            "pv": "1"
        },
        {
            "pagePath": "/categories/Saltの使い方/",
            "pv": "1"
        },
        {
            "pagePath": "/tags/Hugo/",
            "pv": "1"
        },
        {
            "pagePath": "/tags/go-template/",
            "pv": "1"
        }
    ],
    "createdAt": "2025-04-06T00:43:28.015Z"
}