{
    "items": [
        {
            "pagePath": "/article/hugo/tips/",
            "pv": "13"
        },
        {
            "pagePath": "/",
            "pv": "12"
        },
        {
            "pagePath": "/article/hugo/search/",
            "pv": "9"
        },
        {
            "pagePath": "/article/go/go-template/",
            "pv": "4"
        },
        {
            "pagePath": "/categories/サンプル/",
            "pv": "4"
        },
        {
            "pagePath": "/article/salt/about/",
            "pv": "3"
        },
        {
            "pagePath": "/categories/Saltの使い方/",
            "pv": "3"
        },
        {
            "pagePath": "/article/hugo/archive/",
            "pv": "2"
        },
        {
            "pagePath": "/article/sample/hugo-shortcode/",
            "pv": "2"
        },
        {
            "pagePath": "/search/",
            "pv": "2"
        },
        {
            "pagePath": "/article/hugo/build-error/",
            "pv": "1"
        },
        {
            "pagePath": "/article/hugo/fontawesome/",
            "pv": "1"
        },
        {
            "pagePath": "/article/salt/blog-card/",
            "pv": "1"
        },
        {
            "pagePath": "/article/salt/self-blog-card/",
            "pv": "1"
        },
        {
            "pagePath": "/article/sample/no-thumbnail/",
            "pv": "1"
        },
        {
            "pagePath": "/article/sample/small-thumbnail/",
            "pv": "1"
        },
        {
            "pagePath": "/page/2/",
            "pv": "1"
        },
        {
            "pagePath": "/tags/tips/",
            "pv": "1"
        }
    ],
    "createdAt": "2024-09-01T00:40:49.356Z"
}